hazelcast/__init__.py
hazelcast/aggregator.py
hazelcast/asyncore.py
hazelcast/client.py
hazelcast/cluster.py
hazelcast/compact.py
hazelcast/config.py
hazelcast/connection.py
hazelcast/core.py
hazelcast/cp.py
hazelcast/db.py
hazelcast/discovery.py
hazelcast/errors.py
hazelcast/future.py
hazelcast/hash.py
hazelcast/invocation.py
hazelcast/lifecycle.py
hazelcast/listener.py
hazelcast/metrics.py
hazelcast/near_cache.py
hazelcast/partition.py
hazelcast/predicate.py
hazelcast/projection.py
hazelcast/reactor.py
hazelcast/security.py
hazelcast/sql.py
hazelcast/statistics.py
hazelcast/transaction.py
hazelcast/types.py
hazelcast/util.py
hazelcast/vector.py
hazelcast/protocol/__init__.py
hazelcast/protocol/builtin.py
hazelcast/protocol/client_message.py
hazelcast/protocol/codec/__init__.py
hazelcast/protocol/codec/atomic_long_add_and_get_codec.py
hazelcast/protocol/codec/atomic_long_alter_codec.py
hazelcast/protocol/codec/atomic_long_apply_codec.py
hazelcast/protocol/codec/atomic_long_compare_and_set_codec.py
hazelcast/protocol/codec/atomic_long_get_and_add_codec.py
hazelcast/protocol/codec/atomic_long_get_and_set_codec.py
hazelcast/protocol/codec/atomic_long_get_codec.py
hazelcast/protocol/codec/atomic_ref_apply_codec.py
hazelcast/protocol/codec/atomic_ref_compare_and_set_codec.py
hazelcast/protocol/codec/atomic_ref_contains_codec.py
hazelcast/protocol/codec/atomic_ref_get_codec.py
hazelcast/protocol/codec/atomic_ref_set_codec.py
hazelcast/protocol/codec/client_add_cluster_view_listener_codec.py
hazelcast/protocol/codec/client_add_distributed_object_listener_codec.py
hazelcast/protocol/codec/client_authentication_codec.py
hazelcast/protocol/codec/client_authentication_custom_codec.py
hazelcast/protocol/codec/client_create_proxy_codec.py
hazelcast/protocol/codec/client_destroy_proxy_codec.py
hazelcast/protocol/codec/client_fetch_schema_codec.py
hazelcast/protocol/codec/client_get_distributed_objects_codec.py
hazelcast/protocol/codec/client_local_backup_listener_codec.py
hazelcast_python_client-5.5.0.dist-info/LICENSE.txt
hazelcast_python_client-5.5.0.dist-info/METADATA
hazelcast_python_client-5.5.0.dist-info/WHEEL
hazelcast_python_client-5.5.0.dist-info/top_level.txt
hazelcast_python_client-5.5.0.dist-info/RECORD
