Metadata-Version: 2.1
Name: hazelcast-python-client
Version: 5.5.0
Summary: Hazelcast Python Client
Home-page: https://github.com/hazelcast/hazelcast-python-client
Author: Hazelcast Inc. Developers
Author-email: hazelcast@googlegroups.com
License: Apache 2.0
Keywords: hazelcast,hazelcast client,In-Memory Data Grid,Distributed Computing
Classifier: Development Status :: 5 - Production/Stable
Classifier: Intended Audience :: Developers
Classifier: License :: OSI Approved :: Apache Software License
Classifier: Natural Language :: English
Classifier: Operating System :: OS Independent
Classifier: Programming Language :: Python
Classifier: Programming Language :: Python :: 3
Classifier: Programming Language :: Python :: 3 :: Only
Classifier: Programming Language :: Python :: 3.7
Classifier: Programming Language :: Python :: 3.8
Classifier: Programming Language :: Python :: 3.9
Classifier: Programming Language :: Python :: 3.10
Classifier: Programming Language :: Python :: 3.11
Classifier: Programming Language :: Python :: 3.12
Classifier: Programming Language :: Python :: Implementation :: CPython
Classifier: Topic :: Software Development :: Libraries :: Python Modules
License-File: LICENSE.txt
Provides-Extra: stats
Requires-Dist: psutil; extra == "stats"
